fim.cpython-34m.so
pyfim-6.28.dist-info/METADATA
pyfim-6.28.dist-info/WHEEL
pyfim-6.28.dist-info/RECORD
pyfim-6.28.dist-info/top_level.txt
