Metadata-Version: 2.1
Name: pyfim
Version: 6.28
Summary: Frequent Item Set Mining and Association Rule Induction for Python
Home-page: http://www.borgelt.net/pyfim.html
Author: Christian Borgelt
Author-email: christian@borgelt.net
Maintainer: Christian Borgelt
Maintainer-email: christian@borgelt.net
License: MIT License (Expat License)
Download-URL: http://www.borgelt.net/pyfim.html
Platform: Linux/Unix
Platform: Microsoft Windows
